notifications/__init__.py
notifications/factory.py
notifications/notification.py
notifications/notifications.py
notifications/send.py
notifications_tj-0.0.2.dist-info/METADATA
notifications_tj-0.0.2.dist-info/WHEEL
notifications_tj-0.0.2.dist-info/top_level.txt
notifications_tj-0.0.2.dist-info/RECORD
